fds/__init__.py
fds/sdk/__init__.py
fds/sdk/InvestmentBankingOfficeRefresh/__init__.py
fds/sdk/InvestmentBankingOfficeRefresh/api_client.py
fds/sdk/InvestmentBankingOfficeRefresh/configuration.py
fds/sdk/InvestmentBankingOfficeRefresh/exceptions.py
fds/sdk/InvestmentBankingOfficeRefresh/model_utils.py
fds/sdk/InvestmentBankingOfficeRefresh/rest.py
fds/sdk/InvestmentBankingOfficeRefresh/api/__init__.py
fds/sdk/InvestmentBankingOfficeRefresh/api/job_management_api.py
fds/sdk/InvestmentBankingOfficeRefresh/api/refresh_operations_api.py
fds/sdk/InvestmentBankingOfficeRefresh/apis/__init__.py
fds/sdk/InvestmentBankingOfficeRefresh/model/__init__.py
fds/sdk/InvestmentBankingOfficeRefresh/model/active_job_status.py
fds/sdk/InvestmentBankingOfficeRefresh/model/active_job_status_list.py
fds/sdk/InvestmentBankingOfficeRefresh/model/error.py
fds/sdk/InvestmentBankingOfficeRefresh/model/error_code.py
fds/sdk/InvestmentBankingOfficeRefresh/model/errors.py
fds/sdk/InvestmentBankingOfficeRefresh/model/job_status.py
fds/sdk/InvestmentBankingOfficeRefresh/model/job_status_data.py
fds/sdk/InvestmentBankingOfficeRefresh/models/__init__.py
fds.sdk.InvestmentBankingOfficeRefresh-1.1.2.dist-info/LICENSE
fds.sdk.InvestmentBankingOfficeRefresh-1.1.2.dist-info/METADATA
fds.sdk.InvestmentBankingOfficeRefresh-1.1.2.dist-info/WHEEL
fds.sdk.InvestmentBankingOfficeRefresh-1.1.2.dist-info/top_level.txt
fds.sdk.InvestmentBankingOfficeRefresh-1.1.2.dist-info/RECORD
